{
    "sleep": [
        {
            "dateOfSleep": "2017-04-05", 
            "duration": 23940000, 
            "efficiency": 94, 
            "endTime": "2017-04-05T04:52:30.000", 
            "infoCode": 0, 
            "isMainSleep": true, 
            "levels": {
                "data": [
                    {
                        "dateTime": "2017-04-04T22:13:00.000", 
                        "level": "awake", 
                        "seconds": 180
                    }, 
                    {
                        "dateTime": "2017-04-04T22:16:00.000", 
                        "level": "restless", 
                        "seconds": 240
                    }, 
                    {
                        "dateTime": "2017-04-04T22:20:00.000", 
                        "level": "awake", 
                        "seconds": 300
                    }, 
                    {
                        "dateTime": "2017-04-04T22:25:00.000", 
                        "level": "restless", 
                        "seconds": 60
                    }, 
                    {
                        "dateTime": "2017-04-04T22:26:00.000", 
                        "level": "asleep", 
                        "seconds": 1080
                    }, 
                    {
                        "dateTime": "2017-04-04T22:44:00.000", 
                        "level": "restless", 
                        "seconds": 60
                    }, 
                    {
                        "dateTime": "2017-04-04T22:45:00.000", 
                        "level": "asleep", 
                        "seconds": 60
                    }, 
                    {
                        "dateTime": "2017-04-04T22:46:00.000", 
                        "level": "restless", 
                        "seconds": 180
                    }, 
                    {
                        "dateTime": "2017-04-04T22:49:00.000", 
                        "level": "awake", 
                        "seconds": 120
                    }, 
                    {
                        "dateTime": "2017-04-04T22:51:00.000", 
                        "level": "restless", 
                        "seconds": 60
                    }, 
                    {
                        "dateTime": "2017-04-04T22:52:00.000", 
                        "level": "asleep", 
                        "seconds": 6720
                    }, 
                    {
                        "dateTime": "2017-04-05T00:44:00.000", 
                        "level": "restless", 
                        "seconds": 60
                    }, 
                    {
                        "dateTime": "2017-04-05T00:45:00.000", 
                        "level": "asleep", 
                        "seconds": 6180
                    }, 
                    {
                        "dateTime": "2017-04-05T02:28:00.000", 
                        "level": "restless", 
                        "seconds": 60
                    }, 
                    {
                        "dateTime": "2017-04-05T02:29:00.000", 
                        "level": "asleep", 
                        "seconds": 60
                    }, 
                    {
                        "dateTime": "2017-04-05T02:30:00.000", 
                        "level": "restless", 
                        "seconds": 60
                    }, 
                    {
                        "dateTime": "2017-04-05T02:31:00.000", 
                        "level": "asleep", 
                        "seconds": 60
                    }, 
                    {
                        "dateTime": "2017-04-05T02:32:00.000", 
                        "level": "restless", 
                        "seconds": 60
                    }, 
                    {
                        "dateTime": "2017-04-05T02:33:00.000", 
                        "level": "asleep", 
                        "seconds": 780
                    }, 
                    {
                        "dateTime": "2017-04-05T02:46:00.000", 
                        "level": "restless", 
                        "seconds": 60
                    }, 
                    {
                        "dateTime": "2017-04-05T02:47:00.000", 
                        "level": "asleep", 
                        "seconds": 7440
                    }, 
                    {
                        "dateTime": "2017-04-05T04:51:00.000", 
                        "level": "restless", 
                        "seconds": 60
                    }
                ], 
                "summary": {
                    "asleep": {
                        "count": 0, 
                        "minutes": 373
                    }, 
                    "awake": {
                        "count": 3, 
                        "minutes": 10
                    }, 
                    "restless": {
                        "count": 11, 
                        "minutes": 16
                    }
                }
            }, 
            "logId": 14277019236, 
            "minutesAfterWakeup": 1, 
            "minutesAsleep": 373, 
            "minutesAwake": 25, 
            "minutesToFallAsleep": 0, 
            "startTime": "2017-04-04T22:13:00.000", 
            "timeInBed": 399, 
            "type": "classic"
        }
    ], 
    "summary": {
        "totalMinutesAsleep": 373, 
        "totalSleepRecords": 1, 
        "totalTimeInBed": 399
    }
}