{
    "sleep": [
        {
            "dateOfSleep": "2017-04-24", 
            "duration": 22740000, 
            "efficiency": 96, 
            "endTime": "2017-04-24T04:48:00.000", 
            "infoCode": 0, 
            "isMainSleep": true, 
            "levels": {
                "data": [
                    {
                        "dateTime": "2017-04-23T22:28:30.000", 
                        "level": "restless", 
                        "seconds": 60
                    }, 
                    {
                        "dateTime": "2017-04-23T22:29:30.000", 
                        "level": "asleep", 
                        "seconds": 60
                    }, 
                    {
                        "dateTime": "2017-04-23T22:30:30.000", 
                        "level": "restless", 
                        "seconds": 60
                    }, 
                    {
                        "dateTime": "2017-04-23T22:31:30.000", 
                        "level": "asleep", 
                        "seconds": 120
                    }, 
                    {
                        "dateTime": "2017-04-23T22:33:30.000", 
                        "level": "restless", 
                        "seconds": 120
                    }, 
                    {
                        "dateTime": "2017-04-23T22:35:30.000", 
                        "level": "asleep", 
                        "seconds": 780
                    }, 
                    {
                        "dateTime": "2017-04-23T22:48:30.000", 
                        "level": "restless", 
                        "seconds": 60
                    }, 
                    {
                        "dateTime": "2017-04-23T22:49:30.000", 
                        "level": "asleep", 
                        "seconds": 3780
                    }, 
                    {
                        "dateTime": "2017-04-23T23:52:30.000", 
                        "level": "restless", 
                        "seconds": 60
                    }, 
                    {
                        "dateTime": "2017-04-23T23:53:30.000", 
                        "level": "asleep", 
                        "seconds": 1800
                    }, 
                    {
                        "dateTime": "2017-04-24T00:23:30.000", 
                        "level": "restless", 
                        "seconds": 60
                    }, 
                    {
                        "dateTime": "2017-04-24T00:24:30.000", 
                        "level": "asleep", 
                        "seconds": 5280
                    }, 
                    {
                        "dateTime": "2017-04-24T01:52:30.000", 
                        "level": "restless", 
                        "seconds": 240
                    }, 
                    {
                        "dateTime": "2017-04-24T01:56:30.000", 
                        "level": "awake", 
                        "seconds": 180
                    }, 
                    {
                        "dateTime": "2017-04-24T01:59:30.000", 
                        "level": "restless", 
                        "seconds": 60
                    }, 
                    {
                        "dateTime": "2017-04-24T02:00:30.000", 
                        "level": "asleep", 
                        "seconds": 3360
                    }, 
                    {
                        "dateTime": "2017-04-24T02:56:30.000", 
                        "level": "restless", 
                        "seconds": 60
                    }, 
                    {
                        "dateTime": "2017-04-24T02:57:30.000", 
                        "level": "asleep", 
                        "seconds": 5700
                    }, 
                    {
                        "dateTime": "2017-04-24T04:32:30.000", 
                        "level": "restless", 
                        "seconds": 60
                    }, 
                    {
                        "dateTime": "2017-04-24T04:33:30.000", 
                        "level": "asleep", 
                        "seconds": 840
                    }
                ], 
                "summary": {
                    "asleep": {
                        "count": 0, 
                        "minutes": 362
                    }, 
                    "awake": {
                        "count": 1, 
                        "minutes": 3
                    }, 
                    "restless": {
                        "count": 10, 
                        "minutes": 14
                    }
                }
            }, 
            "logId": 14455624666, 
            "minutesAfterWakeup": 0, 
            "minutesAsleep": 362, 
            "minutesAwake": 17, 
            "minutesToFallAsleep": 0, 
            "startTime": "2017-04-23T22:28:30.000", 
            "timeInBed": 379, 
            "type": "classic"
        }
    ], 
    "summary": {
        "totalMinutesAsleep": 362, 
        "totalSleepRecords": 1, 
        "totalTimeInBed": 379
    }
}